<?xml version="1.0" encoding="UTF-8"?>
<SlimOTA xmlns:xsi="http://www.w3.org/2001/XMLSchema-instance" xsi:noNamespaceSchemaLocation="ota.xsd">
    <UNOFFICIAL>
        	<osprey>
			<Filename>XOSP-5.3-UNOFFICIAL-20160422-osprey</Filename>
			<RomUrl
				id="rom"
				title="Rom"
				description="Download the latest XOSP Build">#</RomUrl>
			<OpenGappsUrl
				id="open_gapps"
				title="OpenGApps"
				description="Download latest OpenGApps">http://opengapps.org</OpenGappsUrl>
		</osprey>
    </UNOFFICIAL>   
</SlimOTA>
